{
  "success": true,
  "code": "200",
  "msg": "success",
  "retry": false,
  "data": {
    "dataList": [
      {
        "id": "60f6115c77ce6c000694d110",
        "symbol": "OCEANUSDTM",
        "realisedPnl": 0.6808740000,
        "realisedGrossCost": 0.9540000000,
        "fundingFee": 0.0000000000,
        "dealComm": -0.2731260000,
        "type": "CLOSE_SHORT",
        "currency": "USDT",
        "closeDate": 1626739894361,
        "offset": 2
      },
      {
        "id": "60f60b37635727000664ea81",
        "symbol": "ICPUSDTM",
        "realisedPnl": -1.7410480000,
        "realisedGrossCost": -1.4680000000,
        "fundingFee": 0.0000000000,
        "dealComm": -0.2730480000,
        "type": "CLOSE_LONG",
        "currency": "USDT",
        "closeDate": 1626739046383,
        "offset": 3
      },
      {
        "id": "60f5f8f477ce6c000694b948",
        "symbol": "OCEANUSDTM",
        "realisedPnl": -2.2354260000,
        "realisedGrossCost": -1.6620000000,
        "fundingFee": 0.0000000000,
        "dealComm": -0.5734260000,
        "type": "CLOSE_LONG",
        "currency": "USDT",
        "closeDate": 1626739036264,
        "offset": 4
      },
      {
        "id": "60f5c697d8874200060a4046",
        "symbol": "RVNUSDTM",
        "realisedPnl": 0.1404508400,
        "realisedGrossCost": 0.1987000000,
        "fundingFee": -0.0026935400,
        "dealComm": -0.0555556200,
        "type": "CLOSE_LONG",
        "currency": "USDT",
        "closeDate": 1626739031938,
        "offset": 5
      },
      {
        "id": "6099c2cb4588520006b10592",
        "symbol": "AVAXUSDTM",
        "realisedPnl": 0.8000301000,
        "realisedGrossCost": 0.9520000000,
        "fundingFee": -0.0117415000,
        "dealComm": -0.1402284000,
        "type": "CLOSE_LONG",
        "currency": "USDT",
        "closeDate": 1626738968531,
        "offset": 6
      },
      {
        "id": "60f6006b635727000664c83a",
        "symbol": "ICPUSDTM",
        "realisedPnl": 1.1899392000,
        "realisedGrossCost": 1.4640000000,
        "fundingFee": 0.0000000000,
        "dealComm": -0.2740608000,
        "type": "CLOSE_SHORT",
        "currency": "USDT",
        "closeDate": 1626737463406,
        "offset": 7
      },
      {
        "id": "60f5ffbd635727000664c234",
        "symbol": "DASHUSDTM",
        "realisedPnl": 0.1189291000,
        "realisedGrossCost": 0.1813000000,
        "fundingFee": 0.0000000000,
        "dealComm": -0.0623709000,
        "type": "CLOSE_SHORT",
        "currency": "USDT",
        "closeDate": 1626734927903,
        "offset": 8
      },
      {
        "id": "60f5ec1c6357270006646e82",
        "symbol": "ICPUSDTM",
        "realisedPnl": 2.2230600000,
        "realisedGrossCost": 2.3700000000,
        "fundingFee": 0.0000000000,
        "dealComm": -0.1469400000,
        "type": "CLOSE_LONG",
        "currency": "USDT",
        "closeDate": 1626734699128,
        "offset": 9
      },
      {
        "id": "60f5fece635727000664b665",
        "symbol": "DASHUSDTM",
        "realisedPnl": 0.8032841200,
        "realisedGrossCost": 0.8506000000,
        "fundingFee": 0.0000000000,
        "dealComm": -0.0473158800,
        "type": "CLOSE_LONG",
        "currency": "USDT",
        "closeDate": 1626734525171,
        "offset": 10
      },
      {
        "id": "60f5f0a777ce6c000694aff0",
        "symbol": "MKRUSDTM",
        "realisedPnl": -0.0633376400,
        "realisedGrossCost": -0.0578000000,
        "fundingFee": 0.0000000000,
        "dealComm": -0.0055376400,
        "type": "CLOSE_SHORT",
        "currency": "USDT",
        "closeDate": 1626734321022,
        "offset": 11
      },
      {
        "id": "60a4f6e6aa74cc00066465b8",
        "symbol": "DASHUSDTM",
        "realisedPnl": -1.0403571400,
        "realisedGrossCost": -0.9697000000,
        "fundingFee": 0.0000000000,
        "dealComm": -0.0706571400,
        "type": "CLOSE_SHORT",
        "currency": "USDT",
        "closeDate": 1626734286528,
        "offset": 12
      },
      {
        "id": "60f5f35d77ce6c000694b2c3",
        "symbol": "OCEANUSDTM",
        "realisedPnl": -0.8996728000,
        "realisedGrossCost": -0.6280000000,
        "fundingFee": 0.0000000000,
        "dealComm": -0.2716728000,
        "type": "CLOSE_SHORT",
        "currency": "USDT",
        "closeDate": 1626732788572,
        "offset": 13
      },
      {
        "id": "60a50867aa74cc0006659e5d",
        "symbol": "BATUSDTM",
        "realisedPnl": -0.0700468000,
        "realisedGrossCost": 0.0152000000,
        "fundingFee": -0.0066079200,
        "dealComm": -0.0786388800,
        "type": "CLOSE_LONG",
        "currency": "USDT",
        "closeDate": 1626731402575,
        "offset": 14
      },
      {
        "id": "60f5e3e177ce6c000694a472",
        "symbol": "OCEANUSDTM",
        "realisedPnl": -0.7555680000,
        "realisedGrossCost": 0.0000000000,
        "fundingFee": 0.0000000000,
        "dealComm": -0.7555680000,
        "type": "CLOSE_LONG",
        "currency": "USDT",
        "closeDate": 1626731357289,
        "offset": 15
      },
      {
        "id": "60f5e6e4635727000664603a",
        "symbol": "CHZUSDTM",
        "realisedPnl": -0.2619240000,
        "realisedGrossCost": 0.0000000000,
        "fundingFee": 0.0000000000,
        "dealComm": -0.2619240000,
        "type": "CLOSE_SHORT",
        "currency": "USDT",
        "closeDate": 1626728667011,
        "offset": 16
      },
      {
        "id": "60a0358eaa74cc00064fe83b",
        "symbol": "CHZUSDTM",
        "realisedPnl": 0.6863591300,
        "realisedGrossCost": 0.8565000000,
        "fundingFee": -0.0130587700,
        "dealComm": -0.1570821000,
        "type": "CLOSE_LONG",
        "currency": "USDT",
        "closeDate": 1626728164128,
        "offset": 17
      },
      {
        "id": "60f5e06d77ce6c000694a161",
        "symbol": "OCEANUSDTM",
        "realisedPnl": -0.8823804000,
        "realisedGrossCost": -0.7260000000,
        "fundingFee": 0.0000000000,
        "dealComm": -0.1563804000,
        "type": "CLOSE_SHORT",
        "currency": "USDT",
        "closeDate": 1626727393213,
        "offset": 18
      },
      {
        "id": "60f5d84e77ce6c0006949a47",
        "symbol": "OCEANUSDTM",
        "realisedPnl": -2.1083956000,
        "realisedGrossCost": -1.4380000000,
        "fundingFee": -0.0517680000,
        "dealComm": -0.6186276000,
        "type": "CLOSE_LONG",
        "currency": "USDT",
        "closeDate": 1626726509039,
        "offset": 19
      },
      {
        "id": "60f5cc0277ce6c0006948f3f",
        "symbol": "OCEANUSDTM",
        "realisedPnl": -0.3265464000,
        "realisedGrossCost": 0.0000000000,
        "fundingFee": 0.0000000000,
        "dealComm": -0.3265464000,
        "type": "CLOSE_SHORT",
        "currency": "USDT",
        "closeDate": 1626724430051,
        "offset": 20
      },
      {
        "id": "60a53d3960f8a20006f0ab1b",
        "symbol": "FTMUSDTM",
        "realisedPnl": 0.3674084400,
        "realisedGrossCost": 0.6210000000,
        "fundingFee": 0.0000000000,
        "dealComm": -0.2535915600,
        "type": "CLOSE_LONG",
        "currency": "USDT",
        "closeDate": 1626723511025,
        "offset": 21
      }
    ],
    "hasMore": false
  }
}